examples/__init__.py
examples/test.py
gsxform/__init__.py
gsxform/graph.py
gsxform/kernel.py
gsxform/scattering.py
gsxform/wavelets.py
tests/__init__.py
tests/test_graph.py
tests/test_kernel.py
tests/test_scattering.py
tests/test_utils.py
gsxform-0.1.0.dist-info/LICENSE
gsxform-0.1.0.dist-info/METADATA
gsxform-0.1.0.dist-info/WHEEL
gsxform-0.1.0.dist-info/top_level.txt
gsxform-0.1.0.dist-info/RECORD
