Metadata-Version: 2.1
Name: gsxform
Version: 0.1.0
Summary: Wavelet scattering transforms on graphs via PyTorch
Home-page: https://github.com/armaank/gsxform
Author: Armaan Kohli
Author-email: kohli@cooper.edu
License: BSD 3-Clause
Classifier: Development Status :: 3 - Alpha
Classifier: Programming Language :: Python
Classifier: Programming Language :: Python :: 3.9
Classifier: License :: OSI Approved :: BSD License
Classifier: Intended Audience :: Science/Research
Classifier: Topic :: Scientific/Engineering
Classifier: Topic :: Scientific/Engineering :: Mathematics
License-File: LICENSE
Requires-Dist: einops
Requires-Dist: numpy
Requires-Dist: scipy
Requires-Dist: torch
